pymbolic/__init__.py
pymbolic/algorithm.py
pymbolic/compiler.py
pymbolic/cse.py
pymbolic/functions.py
pymbolic/maxima.py
pymbolic/parser.py
pymbolic/primitives.py
pymbolic/py.typed
pymbolic/rational.py
pymbolic/sympy_interface.py
pymbolic/traits.py
pymbolic/typing.py
pymbolic/version.py
pymbolic/geometric_algebra/__init__.py
pymbolic/geometric_algebra/mapper.py
pymbolic/geometric_algebra/primitives.py
pymbolic/imperative/__init__.py
pymbolic/imperative/analysis.py
pymbolic/imperative/instruction.py
pymbolic/imperative/statement.py
pymbolic/imperative/transform.py
pymbolic/imperative/utils.py
pymbolic/interop/__init__.py
pymbolic/interop/ast.py
pymbolic/interop/common.py
pymbolic/interop/maxima.py
pymbolic/interop/symengine.py
pymbolic/interop/sympy.py
pymbolic/interop/matchpy/__init__.py
pymbolic/interop/matchpy/mapper.py
pymbolic/interop/matchpy/tofrom.py
pymbolic/mapper/__init__.py
pymbolic/mapper/analysis.py
pymbolic/mapper/c_code.py
pymbolic/mapper/coefficient.py
pymbolic/mapper/collector.py
pymbolic/mapper/constant_converter.py
pymbolic/mapper/constant_folder.py
pymbolic/mapper/cse_tagger.py
pymbolic/mapper/dependency.py
pymbolic/mapper/differentiator.py
pymbolic/mapper/distributor.py
pymbolic/mapper/evaluator.py
pymbolic/mapper/flattener.py
pymbolic/mapper/flop_counter.py
pymbolic/mapper/graphviz.py
pymbolic/mapper/optimize.py
pymbolic/mapper/persistent_hash.py
pymbolic/mapper/stringifier.py
pymbolic/mapper/substitutor.py
pymbolic/mapper/unifier.py
pymbolic-2024.2.2.dist-info/METADATA
pymbolic-2024.2.2.dist-info/WHEEL
pymbolic-2024.2.2.dist-info/licenses/LICENSE
pymbolic-2024.2.2.dist-info/RECORD
