Metadata-Version: 2.4
Name: pymbolic
Version: 2024.2.2
Summary: A package for symbolic computation
Project-URL: Documentation, https://documen.tician.de/pymbolic
Project-URL: Homepage, https://github.com/inducer/pymbolic
Author-email: Andreas Kloeckner <inform@tiker.net>
License: MIT
License-File: LICENSE
Classifier: Development Status :: 4 - Beta
Classifier: Intended Audience :: Developers
Classifier: Intended Audience :: Other Audience
Classifier: Intended Audience :: Science/Research
Classifier: License :: OSI Approved :: MIT License
Classifier: Natural Language :: English
Classifier: Programming Language :: Python
Classifier: Programming Language :: Python :: 3 :: Only
Classifier: Topic :: Scientific/Engineering
Classifier: Topic :: Scientific/Engineering :: Mathematics
Classifier: Topic :: Software Development :: Libraries
Classifier: Topic :: Utilities
Requires-Python: >=3.10
Requires-Dist: immutabledict
Requires-Dist: pytools>=2024.1.16
Requires-Dist: typing-extensions>=4.5
Provides-Extra: matchpy
Requires-Dist: matchpy; extra == 'matchpy'
Provides-Extra: numpy
Requires-Dist: numpy>=1.6; extra == 'numpy'
Provides-Extra: test
Requires-Dist: mypy; extra == 'test'
Requires-Dist: pytest; extra == 'test'
Requires-Dist: ruff; extra == 'test'
Requires-Dist: useful-types; extra == 'test'
